ahrs/__init__.py
ahrs/versioning.py
ahrs/common/__init__.py
ahrs/common/constants.py
ahrs/common/dcm.py
ahrs/common/frames.py
ahrs/common/geometry.py
ahrs/common/mathfuncs.py
ahrs/common/orientation.py
ahrs/common/quaternion.py
ahrs/filters/__init__.py
ahrs/filters/angular.py
ahrs/filters/aqua.py
ahrs/filters/complementary.py
ahrs/filters/davenport.py
ahrs/filters/ekf.py
ahrs/filters/famc.py
ahrs/filters/fkf.py
ahrs/filters/flae.py
ahrs/filters/fourati.py
ahrs/filters/fqa.py
ahrs/filters/gravityquaternion.py
ahrs/filters/madgwick.py
ahrs/filters/mahony.py
ahrs/filters/oleq.py
ahrs/filters/quest.py
ahrs/filters/roleq.py
ahrs/filters/saam.py
ahrs/filters/tilt.py
ahrs/filters/triad.py
ahrs/utils/__init__.py
ahrs/utils/io.py
ahrs/utils/metrics.py
ahrs/utils/plot.py
ahrs/utils/wgs84.py
ahrs/utils/wmm.py
ahrs/utils/WMM2015/WMM.COF
ahrs/utils/WMM2020/WMM.COF
AHRS-0.3.1.dist-info/LICENSE
AHRS-0.3.1.dist-info/METADATA
AHRS-0.3.1.dist-info/WHEEL
AHRS-0.3.1.dist-info/top_level.txt
AHRS-0.3.1.dist-info/RECORD
