Metadata-Version: 2.1
Name: AHRS
Version: 0.3.1
Summary: Attitude and Heading Reference Systems.
Home-page: https://github.com/Mayitzin/ahrs/
Author: Mario Garcia
Author-email: mariogc@protonmail.com
License: UNKNOWN
Download-URL: https://github.com/Mayitzin/ahrs/archive/master/ahrs-master.zip
Project-URL: Source Code, https://github.com/Mayitzin/ahrs/
Project-URL: Bug Tracker, https://github.com/Mayitzin/ahrs/issues
Platform: UNKNOWN
Classifier: Development Status :: 3 - Alpha
Classifier: Intended Audience :: Developers
Classifier: Intended Audience :: Education
Classifier: Intended Audience :: Science/Research
Classifier: License :: OSI Approved :: MIT License
Classifier: Operating System :: OS Independent
Classifier: Programming Language :: Python :: 3.6
Classifier: Programming Language :: Python :: 3.7
Classifier: Programming Language :: Python :: 3.8
Classifier: Topic :: Scientific/Engineering
Classifier: Topic :: Scientific/Engineering :: Physics
Classifier: Topic :: Software Development :: Embedded Systems
Classifier: Topic :: Software Development :: Libraries
Classifier: Topic :: Software Development :: Libraries :: Python Modules
License-File: LICENSE
